kevo/__init__.py
kevo/remote.py
kevo/common/__init__.py
kevo/common/bloomfilter.py
kevo/common/fencepointers.py
kevo/common/hashindex.py
kevo/common/ringbuffer.py
kevo/engines/__init__.py
kevo/engines/appendlog.py
kevo/engines/hybridlog.py
kevo/engines/kvstore.py
kevo/engines/lsmtree.py
kevo/engines/memonly.py
kevo-0.2.0.dist-info/METADATA
kevo-0.2.0.dist-info/WHEEL
kevo-0.2.0.dist-info/top_level.txt
kevo-0.2.0.dist-info/RECORD
