Metadata-Version: 2.1
Name: kevo
Version: 0.2.0
Summary: Key-value store with 3 backend engines
Author: Nikos Gavalas
Keywords: key-value,store
Classifier: Programming Language :: Python :: 3
Requires-Python: >=3.11
Requires-Dist: sortedcontainers <3,>=2.4.0
Requires-Dist: bitarray <3,>=2.6.2
Requires-Dist: mmh3 <4,>=3.0.0
Requires-Dist: minio <8,>=7.1.14
